pysvc/__init__.py
pysvc/errors.py
pysvc/examples.py
pysvc/messages.py
pysvc/transports/__init__.py
pysvc/transports/ssh_transport.py
pysvc/transports/transport.py
pysvc/unified/__init__.py
pysvc/unified/client.py
pysvc/unified/clispec.py
pysvc/unified/errors.py
pysvc/unified/response.py
pysvc/unified/scp_cli_client.py
pysvc/unified/xsf-1.0.xml
pysvc/unified/helpers/__init__.py
pysvc/unified/helpers/etree.py
pysvc/unified/helpers/exceptool.py
pysvc/unified/helpers/xml_util.py
pysvc/unified/tests/__init__.py
pysvc/unified/tests/test_scp_cli_client.py
pysvc/unified/tests/test_unified_client.py
pysvc/unified/tests/testdata.py
pysvc2-2.0.2.dist-info/licenses/LICENSE.txt
pysvc2-2.0.2.dist-info/METADATA
pysvc2-2.0.2.dist-info/WHEEL
pysvc2-2.0.2.dist-info/top_level.txt
pysvc2-2.0.2.dist-info/RECORD
